{
  "id": "unit39-page1",
  "pageNumber": 1,
  "lessonHeader": {
    "lessonNumber": 39,
    "pinyin": "",
    "title": "Vocabulary",
    "titleTranslation": "Laughing and crying",
    "titleTranslation_ru": "Laughing and crying"
  },
  "sections": [
    {
      "id": "u39p1-sec-vocab1",
      "type": "grammar",
      "heading": "",
      "subheading": "Topic vocabulary",
      "subheading_uz": "Mavzu lug'ati",
      "subheading_ru": "Тематическая лексика",
      "sentences": [],
      "grammarTableData": {
        "headers": ["", "", ""],
        "rows": [
          {
            "cells": ["amusing (adj)", "embarrassing (adj)", "react (v)"],
            "cells_uz": ["amusing – kulgili, qiziqarli", "embarrassing – uyaladigan, noqulay", "react – munosabat bildirmoq"],
            "cells_ru": ["amusing – забавный, смешной", "embarrassing – смущающий, неловкий", "react – реагировать"]
          },
          {
            "cells": ["annoy (v)", "emotion (n)", "regret (v, n)"],
            "cells_uz": ["annoy – bezovta qilmoq, asablashtirmoq", "emotion – tuyg'u, his", "regret – afsuslanmoq, pushaymon bo'lmoq"],
            "cells_ru": ["annoy – раздражать, беспокоить", "emotion – эмоция, чувство", "regret – сожалеть, сожаление"]
          },
          {
            "cells": ["attitude (n)", "enthusiastic (adj)", "ridiculous (adj)"],
            "cells_uz": ["attitude – munosabat, yondashuv", "enthusiastic – ishtiyoqli, havasmand", "ridiculous – kulgili, bema'ni"],
            "cells_ru": ["attitude – отношение, позиция", "enthusiastic – полный энтузиазма", "ridiculous – смешной, нелепый"]
          },
          {
            "cells": ["bad-tempered (adj)", "feeling (n)", "romantic (adj)"],
            "cells_uz": ["bad-tempered – achchiq, asabiy", "feeling – his-tuyg'u", "romantic – romantik"],
            "cells_ru": ["bad-tempered – раздражительный, злой", "feeling – чувство, ощущение", "romantic – романтичный"]
          },
          {
            "cells": ["behave (v)", "glad (adj)", "rude (adj)"],
            "cells_uz": ["behave – tutunmoq, o'zini tutmoq", "glad – xursand, mamnun", "rude – qo'pol, beadab"],
            "cells_ru": ["behave – вести себя", "glad – рад, довольный", "rude – грубый, невежливый"]
          },
          {
            "cells": ["bully (v, n)", "hurt (v, adj)", "sense of humour (n phr)"],
            "cells_uz": ["bully – bezori, qo'rqitmoq", "hurt – ozor bermoq, xafa bo'lmoq", "sense of humour – hazil tuyg'usi"],
            "cells_ru": ["bully – хулиган, запугивать", "hurt – обижать, обиженный", "sense of humour – чувство юмора"]
          },
          {
            "cells": ["calm (adj)", "miserable (adj)", "shy (adj)"],
            "cells_uz": ["calm – sokin, xotirjam", "miserable – baxtsiz, g'amgin", "shy – uyatchan, tortinchoq"],
            "cells_ru": ["calm – спокойный", "miserable – несчастный, удручённый", "shy – застенчивый, робкий"]
          },
          {
            "cells": ["celebrate (v)", "naughty (adj)", "stress (n)"],
            "cells_uz": ["celebrate – nishonlamoq, bayram qilmoq", "naughty – yomon xulqli, noshud", "stress – stress, tarangsizlik"],
            "cells_ru": ["celebrate – праздновать, отмечать", "naughty – непослушный, шаловливый", "stress – стресс, напряжение"]
          },
          {
            "cells": ["character (n)", "noisy (adj)", "tell a joke (v phr)"],
            "cells_uz": ["character – xarakter, shaxsiyat", "noisy – shovqinli, guldurma", "tell a joke – hazil aytmoq"],
            "cells_ru": ["character – характер, личность", "noisy – шумный", "tell a joke – рассказать анекдот"]
          },
          {
            "cells": ["depressed (adj)", "polite (adj)", "upset (v, adj)"],
            "cells_uz": ["depressed – tushkun, ma'yus", "polite – odobli, muloyim", "upset – xafa qilmoq, xafa"],
            "cells_ru": ["depressed – подавленный, в депрессии", "polite – вежливый", "upset – расстраивать, расстроенный"]
          }
        ]
      }
    },
    {
      "id": "u39p1-sec-phrasal",
      "type": "grammar",
      "heading": "",
      "subheading": "Phrasal verbs",
      "subheading_uz": "Frazeologik fe'llar",
      "subheading_ru": "Фразовые глаголы",
      "sentences": [],
      "grammarTableData": {
        "headers": ["", ""],
        "rows": [
          {
            "cells": ["**calm down**", "become/make calmer"],
            "cells_uz": ["**calm down** – sokinlashmoq / sokinlashtirmoq", "become/make calmer"],
            "cells_ru": ["**calm down** – успокоиться / успокоить", "become/make calmer"]
          },
          {
            "cells": ["**cheer up**", "become/make happier"],
            "cells_uz": ["**cheer up** – xursand bo'lmoq / xursand qilmoq", "become/make happier"],
            "cells_ru": ["**cheer up** – развеселиться / развеселить", "become/make happier"]
          },
          {
            "cells": ["**come on**", "be quicker"],
            "cells_uz": ["**come on** – tezroq bo'lmoq", "be quicker"],
            "cells_ru": ["**come on** – побыстрее, давай", "be quicker"]
          },
          {
            "cells": ["**go on**", "continue happening or doing sth"],
            "cells_uz": ["**go on** – davom etmoq yoki biror narsani qilishda davom etmoq", "continue happening or doing sth"],
            "cells_ru": ["**go on** – продолжаться или продолжать делать что-либо", "continue happening or doing sth"]
          },
          {
            "cells": ["**hang on**", "wait"],
            "cells_uz": ["**hang on** – kutmoq", "wait"],
            "cells_ru": ["**hang on** – подождать", "wait"]
          },
          {
            "cells": ["**run away (from)**", "escape by running"],
            "cells_uz": ["**run away (from)** – qochib ketmoq", "escape by running"],
            "cells_ru": ["**run away (from)** – убежать, сбежать", "escape by running"]
          },
          {
            "cells": ["**shut up**", "stop talking, stop making a noise"],
            "cells_uz": ["**shut up** – gapirmaslik, jim bo'lmoq", "stop talking, stop making a noise"],
            "cells_ru": ["**shut up** – замолчать, прекратить шуметь", "stop talking, stop making a noise"]
          },
          {
            "cells": ["**speak up**", "talk more loudly so sb can hear you"],
            "cells_uz": ["**speak up** – balandroq gapirmoq, eshittirib gapirmoq", "talk more loudly so sb can hear you"],
            "cells_ru": ["**speak up** – говорить громче, чтобы тебя услышали", "talk more loudly so sb can hear you"]
          }
        ]
      }
    },
    {
      "id": "u39p1-sec-prepositions",
      "type": "grammar",
      "heading": "",
      "subheading": "Prepositional phrases",
      "subheading_uz": "Predlogli iboralar",
      "subheading_ru": "Предложные фразы",
      "sentences": [],
      "grammarTableData": {
        "headers": [""],
        "rows": [
          {
            "cells": ["at first"],
            "cells_uz": ["avval, dastlab"],
            "cells_ru": ["сначала, вначале"]
          },
          {
            "cells": ["at least"],
            "cells_uz": ["kamida, hech bo'lmaganda"],
            "cells_ru": ["по крайней мере, хотя бы"]
          },
          {
            "cells": ["at times"],
            "cells_uz": ["ba'zan, gohida"],
            "cells_ru": ["иногда, временами"]
          },
          {
            "cells": ["in secret"],
            "cells_uz": ["sir saqlab, yashirincha"],
            "cells_ru": ["тайно, в секрете"]
          },
          {
            "cells": ["in spite of"],
            "cells_uz": ["qaramay, bo'lishiga qaramay"],
            "cells_ru": ["несмотря на"]
          },
          {
            "cells": ["in tears"],
            "cells_uz": ["ko'z yoshi bilan, yig'lab"],
            "cells_ru": ["в слезах, плача"]
          }
        ]
      }
    },
    {
      "id": "u39p1-sec-wordformation",
      "type": "grammar",
      "heading": "",
      "subheading": "Word formation",
      "subheading_uz": "So'z yasalishi",
      "subheading_ru": "Словообразование",
      "sentences": [],
      "grammarTableData": {
        "headers": ["", "", "", ""],
        "rows": [
          {
            "cells": ["**bore**", "boring, bored", "**feel**", "felt, feeling(s)"],
            "cells_uz": ["**bore**", "zerikarli, zerikkan", "**feel**", "his qildi, his-tuyg'u(lar)"],
            "cells_ru": ["**bore**", "скучный, скучающий", "**feel**", "чувствовал, чувство(а)"]
          },
          {
            "cells": ["**comedy**", "comedian", "**happy**", "unhappy, (un)happiness"],
            "cells_uz": ["**comedy**", "komediyachi", "**happy**", "baxtsiz, (be)baxtlik"],
            "cells_ru": ["**comedy**", "комик, комедиант", "**happy**", "несчастный, (не)счастье"]
          },
          {
            "cells": ["**emotion**", "emotional", "**hate**", "hatred"],
            "cells_uz": ["**emotion**", "hissiy, emotsional", "**hate**", "nafrat"],
            "cells_ru": ["**emotion**", "эмоциональный", "**hate**", "ненависть"]
          },
          {
            "cells": ["**energy**", "energetic", "**noise**", "noisy, noisily"],
            "cells_uz": ["**energy**", "faol, energiyali", "**noise**", "shovqinli, shovqin bilan"],
            "cells_ru": ["**energy**", "энергичный", "**noise**", "шумный, шумно"]
          },
          {
            "cells": ["**excite**", "excitement, exciting, excited", "**sympathy**", "sympathise, sympathetic"],
            "cells_uz": ["**excite**", "hayajon, hayajonli, hayajonda", "**sympathy**", "hamdardlik bildirmoq, hamdard"],
            "cells_ru": ["**excite**", "возбуждение, волнующий, взволнованный", "**sympathy**", "сочувствовать, сочувствующий"]
          }
        ]
      }
    },
    {
      "id": "u39p1-sec-wordpatterns",
      "type": "grammar",
      "heading": "",
      "subheading": "Word patterns",
      "subheading_uz": "So'z birikmalari",
      "subheading_ru": "Словосочетания",
      "sentences": [],
      "grammarTableData": {
        "headers": ["", ""],
        "rows": [
          {
            "cells": ["_adjectives_", "ashamed of\nembarrassed about\nfrightened of\nhappy about/with\nnervous about\nscared of\nsorry about/for\nsurprised at/by\ntired of"],
            "cells_uz": ["_sifatlar_", "... dan uyalgan\n... haqida xijolat bo'lgan\n... dan qo'rqqan\n... dan/bilan xursand\n... haqida asabiy\n... dan cho'chigan\n... haqida/uchun kechirim so'ragan\n... dan/bilan hayron\n... dan charchagan"],
            "cells_ru": ["_прилагательные_", "стыдиться чего-либо\nбыть смущённым из-за\nбояться чего-либо\nбыть рад чему-либо\nнервничать из-за\nбояться чего-либо\nсожалеть о чём-либо\nудивлён чем-либо\nустать от чего-либо"]
          },
          {
            "cells": ["_verbs_", "congratulate sb on\nlaugh at"],
            "cells_uz": ["_fe'llar_", "birovni nima uchundir tabriklamoq\nbiror narsaga kulmoq"],
            "cells_ru": ["_глаголы_", "поздравить кого-либо с чем-либо\nсмеяться над чем-либо"]
          },
          {
            "cells": ["_nouns_", "a joke about"],
            "cells_uz": ["_otlar_", "biror narsa haqida hazil"],
            "cells_ru": ["_существительные_", "шутка о чём-либо"]
          }
        ]
      }
    }
  ]
}
